[
  {
    "_id" : 1,
    "userPhoto":"/images/musk_photo.jpeg",
    "userName": "Elon Musk",
    "at" : "@elonmusk",
    "link" : "",
    "time": "23h",
    "image": "/image/musk_photo.jpeg",
    "content": "Amazing show about",
    "link_content": "@Inspiration4x",
    "content_after_link":"Mission!",
    "shared_title": "Countdown: Inspiration4 Mission to Space | Netflix Official Site",
    "shared_content": "From training to launch to landing, this all-access docuseries rides along with the Inspiration4 crew on the first all-civilian orbital space ...",
    "shared_link": "netflix.com",
    "comments" : "4.2K",
    "share" : "3.5K",
    "like" : "37.5K"
  },
  {
    "_id" : 2,
    "userPhoto":"/images/musk_photo.jpeg",
    "userName": "Elon Musk",
    "at" : "@elonmusk",
    "link" : "",
    "time": "23h",
    "image": "/image/musk_photo.jpeg",
    "content": "Amazing show about",
    "link_content": "@Inspiration4x",
    "content_after_link":"Mission!",
    "shared_title": "Countdown: Inspiration4 Mission to Space | Netflix Official Site",
    "shared_content": "From training to launch to landing, this all-access docuseries rides along with the Inspiration4 crew on the first all-civilian orbital space ...",
    "shared_link": "netflix.com",
    "comments" : "4.2K",
    "share" : "3.5K",
    "like" : "37.5K"
  }
]